<portlet-services>

    <service>
        <name>Portlet Manager Service</name>
        <description>Provides Administration Capabilities for Portlet Web Applications</description>
        <interface>org.gridlab.gridsphere.services.registry.PortletManagerService</interface>
        <implementation>org.gridlab.gridsphere.services.registry.impl.PortletManagerServiceImpl</implementation>
        <service-config>
            <param-name>coreContext</param-name>
            <param-value>coreportlets, gsmanager</param-value>
        </service-config>
    </service>

    <service>
        <name>Login Service</name>
        <description>Provides Login Capabilities</description>
        <interface>org.gridlab.gridsphere.services.user.LoginService</interface>
        <implementation>org.gridlab.gridsphere.services.user.impl.LoginServiceImpl</implementation>
    </service>

    <service>
        <name>Access Control Manager Service</name>
        <user-required>true</user-required>
        <description>Provides Authorization Capabilities to Portal Users</description>
        <interface>org.gridlab.gridsphere.services.security.acl.AccessControlManagerService</interface>
        <implementation>org.gridlab.gridsphere.services.security.acl.impl.AccessControlManagerServiceImpl</implementation>
    </service>

    <service>
        <name>User Account Manager Service</name>
        <user-required>true</user-required>
        <description>Provides User Administration Capabilities</description>
        <interface>org.gridlab.gridsphere.services.user.UserManagerService</interface>
        <implementation>org.gridlab.gridsphere.services.user.impl.UserManagerServiceImpl</implementation>
        <service-config>
            <param-name>userID</param-name>
            <param-value>root</param-value>
        </service-config>
        <service-config>
            <param-name>password</param-name>
            <param-value></param-value>
        </service-config>
    </service>

    <service>
        <name>Password Manager Service</name>
        <description>Provides Password Management Capabilities</description>
        <interface>org.gridlab.gridsphere.services.security.password.PasswordManagerService</interface>
        <implementation>org.gridlab.gridsphere.services.security.password.impl.DbmsPasswordManagerService</implementation>
    </service>

    <service>
        <name>Credential Manager Service</name>
        <description>Provides Credential Management Capabilities</description>
        <interface>org.gridlab.gridsphere.services.security.credential.CredentialManagerService</interface>
        <implementation>org.gridlab.gridsphere.services.security.credential.impl.GlobusCredentialManagerService</implementation>
        <service-config>
            <param-name>retrievalHost</param-name>
            <param-value>myproxy.gridlab.org</param-value>
        </service-config>
    </service>

    <service>
        <name>Layout Service</name>
        <description>Provides Layout Capabilities</description>
        <interface>org.gridlab.gridsphere.services.layout.LayoutManagerService</interface>
        <implementation>org.gridlab.gridsphere.services.layout.impl.LayoutManagerServiceImpl</implementation>
    </service>

</portlet-services>
